LICENSE
README.md
exnd_curses/__init__.py
exnd_curses/actions.py
exnd_curses/read.py
exnd_curses/test.py
exnd_curses/window.py
exnd_curses-0.2.0.dist-info/METADATA
exnd_curses-0.2.0.dist-info/WHEEL
exnd_curses-0.2.0.dist-info/entry_points.txt
exnd_curses-0.2.0.dist-info/licenses/LICENSE
exnd_curses-0.2.0.dist-info/RECORD
